zerogpt/__init__.py
zerogpt/client.py
zerogpt/test.py
zerogpt/utils/__init__.py
zerogpt/utils/cli.py
zerogpt/utils/headers.py
zerogpt/utils/image.py
zerogpt/utils/prompt.py
zerogpt/utils/settings.py
zerogpt/utils/tools/__init__.py
zerogpt/utils/tools/detect_platform.py
zerogpt/utils/tools/image_to_prompt.py
zerogpt-1.3.0.dist-info/licenses/LICENSE
zerogpt-1.3.0.dist-info/METADATA
zerogpt-1.3.0.dist-info/WHEEL
zerogpt-1.3.0.dist-info/top_level.txt
zerogpt-1.3.0.dist-info/RECORD
