Metadata-Version: 2.4
Name: zerogpt
Version: 1.3.0
Summary: Python client for interacting with the ZeroGPT API and generating images.
Home-page: https://github.com/RedPiarOfficial/ZeroGPT
Author: Redpiar
Author-email: Regeonwix@gmail.com
Maintainer: Redpiar
Maintainer-email: Regeonwix@gmail.com
License: MIT
Project-URL: Homepage, https://github.com/RedPiarOfficial/ZeroGPT
Project-URL: Documentation, https://red-3.gitbook.io/zerogpt/
Project-URL: Repository, https://github.com/RedPiarOfficial/ZeroGPT
Project-URL: Bug Tracker, https://github.com/RedPiarOfficial/ZeroGPT/issues
Keywords: ai,zerogpt,arting,text,image,free,api,uncensured,gpt,deepseek,chatgpt
Classifier: Development Status :: 4 - Beta
Classifier: Intended Audience :: Developers
Classifier: License :: OSI Approved :: MIT License
Classifier: Operating System :: OS Independent
Classifier: Programming Language :: Python :: 3
Classifier: Programming Language :: Python :: 3.8
Classifier: Programming Language :: Python :: 3.9
Classifier: Programming Language :: Python :: 3.10
Classifier: Programming Language :: Python :: 3.11
Classifier: Programming Language :: Python :: 3.12
Classifier: Topic :: Software Development :: Libraries :: Python Modules
Classifier: Topic :: Scientific/Engineering :: Artificial Intelligence
Requires-Python: >=3.8
License-File: LICENSE
Requires-Dist: requests
Requires-Dist: httpx
Requires-Dist: httpx[http2]
Requires-Dist: fake_useragent
Requires-Dist: pandas
Requires-Dist: requests_toolbelt
Requires-Dist: packaging
Requires-Dist: urlextract
Provides-Extra: dev
Requires-Dist: pytest>=7.0; extra == "dev"
Requires-Dist: pytest-cov>=4.0; extra == "dev"
Requires-Dist: black>=22.0; extra == "dev"
Requires-Dist: flake8>=5.0; extra == "dev"
Requires-Dist: mypy>=1.0; extra == "dev"
Dynamic: author
Dynamic: author-email
Dynamic: classifier
Dynamic: description
Dynamic: description-content-type
Dynamic: home-page
Dynamic: keywords
Dynamic: license
Dynamic: license-file
Dynamic: maintainer
Dynamic: maintainer-email
Dynamic: project-url
Dynamic: provides-extra
Dynamic: requires-dist
Dynamic: requires-python
Dynamic: summary
